AdvancedCalculate/__init__.py
AdvancedCalculate/calculate.py
advanced_calculate-0.0.1.dist-info/METADATA
advanced_calculate-0.0.1.dist-info/WHEEL
advanced_calculate-0.0.1.dist-info/top_level.txt
advanced_calculate-0.0.1.dist-info/RECORD
