Metadata-Version: 2.1
Name: advanced-calculate
Version: 0.0.1
Summary: Advanced calculator written in Python
Home-page: https://gitlab.com/kubatbaew
Author: kubatbaew
Author-email: kubatbaew@gmail.com
License: UNKNOWN
Keywords: calculate advanced
Platform: UNKNOWN
Classifier: Programming Language :: Python :: 3.11
Classifier: License :: OSI Approved :: MIT License
Classifier: Operating System :: OS Independent
